ananse/__init__.py
ananse/ananse.py
ananse-1.1.2.dist-info/METADATA
ananse-1.1.2.dist-info/WHEEL
ananse-1.1.2.dist-info/top_level.txt
ananse-1.1.2.dist-info/RECORD
