Metadata-Version: 2.1
Name: ananse
Version: 1.1.2
Summary: A python package to partially automate search term selection and writing search strategies for systematic reviews
Home-page: UNKNOWN
Author: Bernard Atiemo Asare, Amma Frimpomaa Frimpong-Boateng, Dr Wiafe Owusu-Banahene, Dr. Effah Antwi
Author-email: asarebernard98@gmail.com, Ammafrimps123@gmail.com
License: UNKNOWN
Project-URL: Documentation, https://baasare.github.io/ananse/
Project-URL: Source Code, https://github.com/baasare/ananse
Platform: UNKNOWN
Classifier: Development Status :: 3 - Alpha
Classifier: Intended Audience :: Education
Classifier: Operating System :: OS Independent
Classifier: Programming Language :: Python :: 3.7
Requires: bleach
Requires: certifi
Requires: cycler
Requires: decorator
Requires: docutils
Requires: importlib_metadata
Requires: joblib
Requires: keyring
Requires: kiwisolver
Requires: matplotlib
Requires: more_itertools
Requires: networkx
Requires: nltk
Requires: numpy
Requires: pandas
Requires: pkginfo
Requires: Pygments
Requires: pyparsing
Requires: python_dateutil
Requires: pytz
Requires: pywin32_ctypes
Requires: rake_nltk
Requires: RISparser
Requires: readme_renderer
Requires: requests_toolbelt
Requires: scikit_learn
Requires: scipy
Requires: six
Requires: sklearn
Requires: tqdm
Requires: twine
Requires: webencodings
Requires: wincertstore
Requires: zipp
Requires-Dist: bleach
Requires-Dist: certifi
Requires-Dist: cycler
Requires-Dist: decorator
Requires-Dist: docutils
Requires-Dist: importlib-metadata
Requires-Dist: joblib
Requires-Dist: keyring
Requires-Dist: kiwisolver
Requires-Dist: matplotlib
Requires-Dist: more-itertools
Requires-Dist: networkx
Requires-Dist: nltk
Requires-Dist: numpy
Requires-Dist: pandas
Requires-Dist: pkginfo
Requires-Dist: Pygments
Requires-Dist: pyparsing
Requires-Dist: python-dateutil
Requires-Dist: pytz
Requires-Dist: pywin32-ctypes
Requires-Dist: rake-nltk
Requires-Dist: RISparser
Requires-Dist: readme-renderer
Requires-Dist: requests-toolbelt
Requires-Dist: scikit-learn
Requires-Dist: scipy
Requires-Dist: six
Requires-Dist: sklearn
Requires-Dist: tqdm
Requires-Dist: twine
Requires-Dist: webencodings
Requires-Dist: wincertstore
Requires-Dist: zipp
